pynewsml/__init__.py
pynewsml/newsml.py
pynewsml-1.4.0.dist-info/METADATA
pynewsml-1.4.0.dist-info/WHEEL
pynewsml-1.4.0.dist-info/RECORD
